spider_domainauth/__init__.py
spider_domainauth/abstract_models.py
spider_domainauth/apps.py
spider_domainauth/migrations/0001_initial.py
spider_domainauth/migrations/__init__.py
spider_domainauth/models.py
spider_domainauth/urls.py
spider_domainauth/utils.py
spider_domainauth/views.py
spkcspider_domainauth-0.6.2.dist-info/WHEEL
spkcspider_domainauth-0.6.2.dist-info/METADATA
spkcspider_domainauth-0.6.2.dist-info/RECORD
