Metadata-Version: 2.1
Name: spkcspider-domainauth
Version: 0.6.2
Summary: Helper for spkcspiders domain authentication
Home-page: https://github.com/spkcspider/spkcspider-domainauth
Author: Alexander Kaftan
Requires-Python: >=3.5
Classifier: Programming Language :: Python :: 3
Classifier: Programming Language :: Python :: 3.5
Classifier: Programming Language :: Python :: 3.6
Classifier: Programming Language :: Python :: 3.7
Provides-Extra: ratelimit
Provides-Extra: spkcspider
Provides-Extra: test
Requires-Dist: django (>=2.0)
Project-URL: Repository, https://github.com/spkcspider/spkcspider-domainauth
